coloramaeasy/__init__.py
colorama_easy-0.1.0.dist-info/WHEEL
colorama_easy-0.1.0.dist-info/METADATA
colorama_easy-0.1.0.dist-info/RECORD
