Metadata-Version: 2.1
Name: colorama-easy
Version: 0.1.0
Summary: 
License: MIT
Author: xmonader
Author-email: xmonader@gmail.com
Requires-Python: >=3.7,<4.0
Classifier: License :: OSI Approved :: MIT License
Classifier: Programming Language :: Python :: 3
Classifier: Programming Language :: Python :: 3.7
Requires-Dist: colorama (>=0.4.1,<0.5.0)
